mlpreprocessor/__init__.py
mlpreprocessor/__main__.py
mlpreprocessor/version.py
mlpreprocessor/file/__init__.py
mlpreprocessor/file/base.py
mlpreprocessor/image/__init__.py
mlpreprocessor/image/base.py
mlpreprocessor-0.0.5.dist-info/LICENSE
mlpreprocessor-0.0.5.dist-info/METADATA
mlpreprocessor-0.0.5.dist-info/WHEEL
mlpreprocessor-0.0.5.dist-info/top_level.txt
mlpreprocessor-0.0.5.dist-info/RECORD
