Metadata-Version: 2.1
Name: mlpreprocessor
Version: 0.0.5
Summary: Exposed interface tool for accessing vpc controller api
Author: wangziling100
Author-email: wangziling100@163.com
Classifier: Programming Language :: Python :: 3
Classifier: License :: OSI Approved :: MIT License
License-File: LICENSE
